{"consensus_set_id":"14959","translation_language":"fa","translation_source":{"hid":"106936"},"segments":[{"source_hadith_segment":"جَاءَ رَجُلٌ اِلَي اَبِي ذَرٍّ فَقَالَ يَا اَبَا ذَرٍّ مَا لَنَا نَكْرَهُ الْمَوْتَ","translation_segment":"حضرت صادق علیه السلام فرمود: مردی پیش أبی ذر آمد و گفت: ای ابا ذر چگونه","segment_columns":[{"kind":"word","token":"و","display":"وَ"},{"kind":"word","token":"جاء","display":"جَاءَ"},{"kind":"word","token":"رجل","display":"رَجُلٌ"},{"kind":"word","token":"الي","display":"اِلَي"},{"kind":"word","token":"ابي","display":"اَبِي"},{"kind":"word","token":"ذر","display":"ذَرٍّ"},{"kind":"word","token":"ره","display":"ره"},{"kind":"word","token":"فقال","display":"فَقَالَ"},{"kind":"word","token":"له","display":"لَهُ"},{"kind":"word","token":"يا","display":"يَا"},{"kind":"word","token":"ابا","display":"اَبَا"},{"kind":"word","token":"ذر","display":"ذَرٍّ"},{"kind":"word","token":"-","display":"-"},{"kind":"word","token":"رحمه","display":"رَحِمَهُ"},{"kind":"word","token":"الله","display":"اللَّهُ"},{"kind":"word","token":"عليه","display":"عَلَيْهِ"},{"kind":"word","token":"-","display":"-"},{"kind":"word","token":"ما","display":"مَا"},{"kind":"word","token":"لنا","display":"لَنَا"},{"kind":"word","token":"نكره","display":"نَكْرَهُ"},{"kind":"word","token":"الموت","display":"الْمَوْتَ"}]},{"source_hadith_segment":"فَقَالَ لِاَنَّكُمْ عَمَرْتُمُ الدُّنْيَا وَ اَخْرَبْتُمُ الْاخِرَةَ","translation_segment":"است که ما مرگ را بد (و ناخوش) داریم‌؟ گفت: زیرا شما دنیا","segment_columns":[{"kind":"word","token":"فقال","display":"فَقَالَ"},{"kind":"word","token":"لانكم","display":"لِاَنَّكُمْ"},{"kind":"word","token":"عمرتم","display":"عَمَرْتُمُ"},{"kind":"word","token":"الدنيا","display":"الدُّنْيَا"},{"kind":"word","token":"و","display":"وَ"},{"kind":"word","token":"اخربتم","display":"اَخْرَبْتُمُ"},{"kind":"word","token":"الاخره","display":"الْاخِرَةَ"}]},{"source_hadith_segment":"فَتَكْرَهُونَ اَنْ تُنْقَلُوا مِنْ عُمْرَانٍ اِلَي خَرَابٍ","translation_segment":"را آباد کرده‌اید و آخرت را ویران ساخته‌اید و خوش","segment_columns":[{"kind":"word","token":"فتكرهون","display":"فَتَكْرَهُونَ"},{"kind":"word","token":"ان","display":"اَنْ"},{"kind":"word","token":"تنقلوا","display":"تُنْقَلُوا"},{"kind":"word","token":"من","display":"مِنْ"},{"kind":"word","token":"عمران","display":"عُمْرَانٍ"},{"kind":"word","token":"الي","display":"اِلَي"},{"kind":"word","token":"خراب","display":"خَرَابٍ"},{"kind":"word","token":"و","display":"وَ"}]},{"source_hadith_segment":"فَقَالَ لَهُ فَكَيْفَ تَرَي قُدُومَنَا عَلَي اللَّهِ","translation_segment":"ندارید که از (خانه) آبادان بمنزل ویران روید","segment_columns":[{"kind":"word","token":"فقال","display":"فَقَالَ"},{"kind":"word","token":"له","display":"لَهُ"},{"kind":"word","token":"فكيف","display":"فَكَيْفَ"},{"kind":"word","token":"تري","display":"تَرَي"},{"kind":"word","token":"قدومنا","display":"قُدُومَنَا"},{"kind":"word","token":"علي","display":"عَلَي"},{"kind":"word","token":"الله","display":"اللَّهِ"},{"kind":"word","token":"عز","display":"عَزَّ"},{"kind":"word","token":"و","display":"وَ"},{"kind":"word","token":"جل","display":"جَلَّ"}]},{"source_hadith_segment":"فَقَالَ اَمَّا الْمُحْسِنُ مِنْكُمْ فَكَالْغَائِبِ يَقْدَمُ عَلَي اَهْلِهِ","translation_segment":"(آن مرد) از او پرسید: ورود ما را بر خداوند چگونه بینی‌؟ گفت:","segment_columns":[{"kind":"word","token":"فقال","display":"فَقَالَ"},{"kind":"word","token":"اما","display":"اَمَّا"},{"kind":"word","token":"المحسن","display":"الْمُحْسِنُ"},{"kind":"word","token":"منكم","display":"مِنْكُمْ"},{"kind":"word","token":"فكالغائب","display":"فَكَالْغَائِبِ"},{"kind":"word","token":"يقدم","display":"يَقْدَمُ"},{"kind":"word","token":"علي","display":"عَلَي"},{"kind":"word","token":"اهله","display":"اَهْلِهِ"},{"kind":"word","token":"-","display":"-"}]},{"source_hadith_segment":"وَ اَمَّا الْمُسِيءُ مِنْكُمْ فَكَالْابِقِ يَرِدُ عَلَي مَوْلاَهُ","translation_segment":"اما نیکوکاران شما مانند مسافری است که بخاندان خود وارد","segment_columns":[{"kind":"word","token":"و","display":"وَ"},{"kind":"word","token":"اما","display":"اَمَّا"},{"kind":"word","token":"المسيء","display":"الْمُسِيءُ"},{"kind":"word","token":"منكم","display":"مِنْكُمْ"},{"kind":"word","token":"فكالابق","display":"فَكَالْابِقِ"},{"kind":"word","token":"يرد","display":"يَرِدُ"},{"kind":"word","token":"علي","display":"عَلَي"},{"kind":"word","token":"مولاه","display":"مَوْلاَهُ"}]},{"source_hadith_segment":"قَالَ فَكَيْفَ تَرَي حَالَنَا عِنْدَ اللَّهِ","translation_segment":"شود، و اما بدکرداران (و گنهکاران) شما","segment_columns":[{"kind":"word","token":"قال","display":"قَالَ"},{"kind":"word","token":"فكيف","display":"فَكَيْفَ"},{"kind":"word","token":"تري","display":"تَرَي"},{"kind":"word","token":"حالنا","display":"حَالَنَا"},{"kind":"word","token":"عند","display":"عِنْدَ"},{"kind":"word","token":"الله","display":"اللَّهِ"},{"kind":"word","token":"تعالي","display":"تَعَالَي"}]},{"source_hadith_segment":"قَالَ اِعْرِضُوا اَعْمَالَكُمْ عَلَي الْكِتَابِ","translation_segment":"چون بنده گریخته ایست که نزد آقایش","segment_columns":[{"kind":"word","token":"قال","display":"قَالَ"},{"kind":"word","token":"اعرضوا","display":"اِعْرِضُوا"},{"kind":"word","token":"اعمالكم","display":"اَعْمَالَكُمْ"},{"kind":"word","token":"علي","display":"عَلَي"},{"kind":"word","token":"الكتاب","display":"الْكِتَابِ"},{"kind":"word","token":"ان","display":"ان"}]},{"source_hadith_segment":"اِنَّ اللَّهَ يَقُولُ :   <quranic_text> « اِنَّ الْاَبْرٰارَ لَفِي نَعِيمٍ وَ اِنَّ الْفُجّٰارَ لَفِي جَحِيمٍ » </quranic_text>   <footnote> [ الانفطار ۱۳ ] </footnote>","translation_segment":"بازگردانند، گفت: حال ما را نزد خداوند چگونه بینی‌؟ گفت: کردارتان را بر قرآن عرضه کنید (و بوسیله آن سنجش کنید) خداوند (در قرآن)","segment_columns":[{"kind":"word","token":"ان","display":"اِنَّ"},{"kind":"word","token":"يقول","display":"يَقُولُ"},{"kind":"word","token":"الله","display":"اللَّهَ"},{"kind":"word","token":"تبارك","display":"تَبَارَكَ"},{"kind":"word","token":"و","display":"وَ"},{"kind":"word","token":"تعالي","display":"تَعَالَي"},{"kind":"word","token":"يقول","display":"يَقُولُ"},{"kind":"tag_open","tag_name":"quranic_text"},{"kind":"word","token":"ان","display":"اِنَّ"},{"kind":"word","token":"الابرار","display":"الْاَبْرٰارَ"},{"kind":"word","token":"لفي","display":"لَفِي"},{"kind":"word","token":"نعيم","display":"نَعِيمٍ"},{"kind":"word","token":"و","display":"وَ"},{"kind":"word","token":"ان","display":"اِنَّ"},{"kind":"word","token":"الفجار","display":"الْفُجّٰارَ"},{"kind":"word","token":"لفي","display":"لَفِي"},{"kind":"word","token":"جحيم","display":"جَحِيمٍ"},{"kind":"tag_close","tag_name":"quranic_text"},{"kind":"tag_open","tag_name":"footnote"},{"kind":"word","token":"الانفطار","display":"الانفطار"},{"kind":"word","token":"۱۳","display":"۱۳"},{"kind":"tag_close","tag_name":"footnote"}]},{"source_hadith_segment":"قَالَ فَقَالَ الرَّجُلُ فَاَيْنَ رَحْمَةُ اللَّهِ","translation_segment":"فرماید: «همانا نیکان در نعمتها هستند، و همانا گنهکاران در","segment_columns":[{"kind":"word","token":"قال","display":"قَالَ"},{"kind":"word","token":"فقال","display":"فَقَالَ"},{"kind":"word","token":"الرجل","display":"الرَّجُلُ"},{"kind":"word","token":"فاين","display":"فَاَيْنَ"},{"kind":"word","token":"رحمه","display":"رَحْمَةُ"},{"kind":"word","token":"الله","display":"اللَّهِ"}]},{"source_hadith_segment":"قَالَ رَحْمَةُ اللَّهِ  <quranic_text> « قَرِيبٌ مِنَ الْمُحْسِنِينَ » </quranic_text>   <footnote> [ الاعراف ۵۶ ] </footnote>","translation_segment":"دوزخند» (سوره انفطار آیه ۱۳ - ۱۴) حضرت فرمود: پس آن مرد گفت: پس رحمت خدا کجاست‌؟ فرمود در","segment_columns":[{"kind":"word","token":"قال","display":"قَالَ"},{"kind":"word","token":"ان","display":"اِنَّ"},{"kind":"word","token":"رحمه","display":"رَحْمَةُ"},{"kind":"word","token":"الله","display":"اللَّهِ"},{"kind":"tag_open","tag_name":"quranic_text"},{"kind":"word","token":"قريب","display":"قَرِيبٌ"},{"kind":"word","token":"من","display":"مِنَ"},{"kind":"word","token":"المحسنين","display":"الْمُحْسِنِينَ"},{"kind":"tag_close","tag_name":"quranic_text"},{"kind":"tag_open","tag_name":"footnote"},{"kind":"word","token":"الاعراف","display":"الاعراف"},{"kind":"word","token":"۵۶","display":"۵۶"},{"kind":"tag_close","tag_name":"footnote"}]},{"source_hadith_segment":"قَالَ اَبُو عَبْدِ اللَّهِ عَلَيْهِ السَّلاَمُ وَ كَتَبَ رَجُلٌ اِلَي اَبِي ذَرٍّ رَضِيَ اللَّهُ عَنْهُ","translation_segment":"رحمت خدا به نیکوکاران نزدیک است (یعنی باید مستحق رحمت باشد تا باو برسد). و نیز امام صادق علیه السلام","segment_columns":[{"kind":"word","token":"قال","display":"قَالَ"},{"kind":"word","token":"ابو","display":"اَبُو"},{"kind":"word","token":"عبد","display":"عَبْدِ"},{"kind":"word","token":"الله","display":"اللَّهِ"},{"kind":"word","token":"عليه","display":"عَلَيْهِ"},{"kind":"word","token":"السلام","display":"السَّلاَمُ"},{"kind":"word","token":"و","display":"وَ"},{"kind":"word","token":"كتب","display":"كَتَبَ"},{"kind":"word","token":"رجل","display":"رَجُلٌ"},{"kind":"word","token":"الي","display":"اِلَي"},{"kind":"word","token":"ابي","display":"اَبِي"},{"kind":"word","token":"ذر","display":"ذَرٍّ"},{"kind":"word","token":"رضي","display":"رَضِيَ"},{"kind":"word","token":"الله","display":"اللَّهُ"},{"kind":"word","token":"عنه","display":"عَنْهُ"}]},{"source_hadith_segment":"يَا اَبَا ذَرٍّ اَطْرِفْنِي بِشَيْءٍ مِنَ الْعِلْمِ","translation_segment":"فرمود: مردی بابی ذر نوشت: ای ابا ذر چیزی از","segment_columns":[{"kind":"word","token":"يا","display":"يَا"},{"kind":"word","token":"ابا","display":"اَبَا"},{"kind":"word","token":"ذر","display":"ذَرٍّ"},{"kind":"word","token":"اطرفني","display":"اَطْرِفْنِي"},{"kind":"word","token":"بشيء","display":"بِشَيْءٍ"},{"kind":"word","token":"من","display":"مِنَ"},{"kind":"word","token":"العلم","display":"الْعِلْمِ"}]},{"source_hadith_segment":"فَكَتَبَ اِلَيْهِ اَنَّ الْعِلْمَ كَثِيرٌ وَ لَكِنْ اِنْ قَدَرْتَ اَنْ لاَ تُسِيءَ اِلَي مَنْ تُحِبُّهُ فَافْعَلْ","translation_segment":"علم بمن تحفه بده، در جوابش نوشت: همانا علم بسیار است ولی اگر بتوانی بآن که دوستش داری بدی نکنی،","segment_columns":[{"kind":"word","token":"فكتب","display":"فَكَتَبَ"},{"kind":"word","token":"اليه","display":"اِلَيْهِ"},{"kind":"word","token":"ان","display":"اَنَّ"},{"kind":"word","token":"العلم","display":"الْعِلْمَ"},{"kind":"word","token":"كثير","display":"كَثِيرٌ"},{"kind":"word","token":"و","display":"وَ"},{"kind":"word","token":"لكن","display":"لَكِنْ"},{"kind":"word","token":"ان","display":"اِنْ"},{"kind":"word","token":"قدرت","display":"قَدَرْتَ"},{"kind":"word","token":"ان","display":"اَنْ"},{"kind":"word","token":"لا","display":"لاَ"},{"kind":"word","token":"تسيء","display":"تُسِيءَ"},{"kind":"word","token":"الي","display":"اِلَي"},{"kind":"word","token":"من","display":"مَنْ"},{"kind":"word","token":"تحبه","display":"تُحِبُّهُ"},{"kind":"word","token":"فافعل","display":"فَافْعَلْ"}]},{"source_hadith_segment":"قَالَ فَقَالَ لَهُ الرَّجُلُ وَ هَلْ رَاَيْتَ اَحَداً يُسِيءُ اِلَي مَنْ يُحِبُّهُ","translation_segment":"آن را بکن، آن مرد گفت: آیا تاکنون کسی را دیده‌ای که بآن که دوستش دارد","segment_columns":[{"kind":"word","token":"قال","display":"قَالَ"},{"kind":"word","token":"فقال","display":"فَقَالَ"},{"kind":"word","token":"له","display":"لَهُ"},{"kind":"word","token":"الرجل","display":"الرَّجُلُ"},{"kind":"word","token":"و","display":"وَ"},{"kind":"word","token":"هل","display":"هَلْ"},{"kind":"word","token":"رايت","display":"رَاَيْتَ"},{"kind":"word","token":"احدا","display":"اَحَداً"},{"kind":"word","token":"يسيء","display":"يُسِيءُ"},{"kind":"word","token":"الي","display":"اِلَي"},{"kind":"word","token":"من","display":"مَنْ"},{"kind":"word","token":"يحبه","display":"يُحِبُّهُ"}]},{"source_hadith_segment":"فَقَالَ لَهُ نَعَمْ نَفْسُكَ اَحَبُّ الْاَنْفُسِ اِلَيْكَ","translation_segment":"بدی کند؟ گفت: آری تو خود را از همه کس بیشتر","segment_columns":[{"kind":"word","token":"فقال","display":"فَقَالَ"},{"kind":"word","token":"له","display":"لَهُ"},{"kind":"word","token":"نعم","display":"نَعَمْ"},{"kind":"word","token":"نفسك","display":"نَفْسُكَ"},{"kind":"word","token":"احب","display":"اَحَبُّ"},{"kind":"word","token":"الانفس","display":"الْاَنْفُسِ"},{"kind":"word","token":"اليك","display":"اِلَيْكَ"}]},{"source_hadith_segment":"فَاِذَا اَنْتَ عَصَيْتَ اللَّهَ فَقَدْ اَسَاْتَ اِلَيْهَا .","translation_segment":"دوست داری، و چون نافرمانی خدا کنی بدای بدی کرده‌ای.","segment_columns":[{"kind":"word","token":"فاذا","display":"فَاِذَا"},{"kind":"word","token":"انت","display":"اَنْتَ"},{"kind":"word","token":"عصيت","display":"عَصَيْتَ"},{"kind":"word","token":"الله","display":"اللَّهَ"},{"kind":"word","token":"فقد","display":"فَقَدْ"},{"kind":"word","token":"اسات","display":"اَسَاْتَ"},{"kind":"word","token":"اليها","display":"اِلَيْهَا"}]}]}