{"consensus_set_id":"51536","translation_language":"fa","translation_source":{"hid":"66735"},"segments":[{"source_hadith_segment":"قلت لابي جعفر الباقر عليه السّلام :  انتم ورثة رسول اللّه صلّي اللّه عليه و اله","translation_segment":"","segment_columns":[{"kind":"word","token":"و","display":"و"},{"kind":"word","token":"كان","display":"كان"},{"kind":"word","token":"ضريرا","display":"ضريرا"},{"kind":"word","token":"و","display":"و"},{"kind":"word","token":"قيل","display":"قيل"},{"kind":"word","token":"اكمه","display":"اكمه"},{"kind":"word","token":"قال","display":"قال"},{"kind":"word","token":"قلت","display":"قلت"},{"kind":"word","token":"لابي","display":"لابي"},{"kind":"word","token":"جعفر","display":"جعفر"},{"kind":"word","token":"الباقر","display":"الباقر"},{"kind":"word","token":"عليه","display":"عليه"},{"kind":"word","token":"السلام","display":"السّلام"},{"kind":"word","token":"انتم","display":"انتم"},{"kind":"word","token":"ورثه","display":"ورثة"},{"kind":"word","token":"رسول","display":"رسول"},{"kind":"word","token":"الله","display":"اللّه"},{"kind":"word","token":"صلي","display":"صلّي"},{"kind":"word","token":"الله","display":"اللّه"},{"kind":"word","token":"عليه","display":"عليه"},{"kind":"word","token":"و","display":"و"},{"kind":"word","token":"اله","display":"اله"}]},{"source_hadith_segment":"؟  فقال لي :  نعم رسول اللّه وارث الانبياء ،  و نحن ورثته و ورثتهم .  فقلت","translation_segment":"","segment_columns":[{"kind":"word","token":"فقال","display":"فقال"},{"kind":"word","token":"لي","display":"لي"},{"kind":"word","token":"نعم","display":"نعم"},{"kind":"word","token":"رسول","display":"رسول"},{"kind":"word","token":"الله","display":"اللّه"},{"kind":"word","token":"وارث","display":"وارث"},{"kind":"word","token":"الانبياء","display":"الانبياء"},{"kind":"word","token":"صلوات","display":"صلوات"},{"kind":"word","token":"الله","display":"اللّه"},{"kind":"word","token":"عليهم","display":"عليهم"},{"kind":"word","token":"و","display":"و"},{"kind":"word","token":"نحن","display":"نحن"},{"kind":"word","token":"ورثته","display":"ورثته"},{"kind":"word","token":"و","display":"و"},{"kind":"word","token":"ورثتهم","display":"ورثتهم"},{"kind":"word","token":"فقلت","display":"فقلت"}]},{"source_hadith_segment":":  تقدرون ان تحيوا الموتي و تبرءوا الاكمه و الابرص","translation_segment":"","segment_columns":[{"kind":"word","token":"تقدرون","display":"تقدرون"},{"kind":"word","token":"ان","display":"ان"},{"kind":"word","token":"تحيوا","display":"تحيوا"},{"kind":"word","token":"الموتي","display":"الموتي"},{"kind":"word","token":"و","display":"و"},{"kind":"word","token":"تبرءوا","display":"تبرءوا"},{"kind":"word","token":"الاكمه","display":"الاكمه"},{"kind":"word","token":"و","display":"و"},{"kind":"word","token":"الابرص","display":"الابرص"}]},{"source_hadith_segment":"؟  فقال :  نعم باذن اللّه تعالي .  ثمّ قال","translation_segment":"","segment_columns":[{"kind":"word","token":"فقال","display":"فقال"},{"kind":"word","token":"نعم","display":"نعم"},{"kind":"word","token":"باذن","display":"باذن"},{"kind":"word","token":"الله","display":"اللّه"},{"kind":"word","token":"تعالي","display":"تعالي"},{"kind":"word","token":"ثم","display":"ثمّ"},{"kind":"word","token":"قال","display":"قال"}]},{"source_hadith_segment":":  ادن منّي .  فدنوت منه عليه السّلام فمسح علي عيني ،  فابصرت السماء و الارض ،  و كلّ شيء كان","translation_segment":"","segment_columns":[{"kind":"word","token":"ادن","display":"ادن"},{"kind":"word","token":"مني","display":"منّي"},{"kind":"word","token":"فدنوت","display":"فدنوت"},{"kind":"word","token":"منه","display":"منه"},{"kind":"word","token":"عليه","display":"عليه"},{"kind":"word","token":"السلام","display":"السّلام"},{"kind":"word","token":"فمسح","display":"فمسح"},{"kind":"word","token":"علي","display":"علي"},{"kind":"word","token":"عيني","display":"عيني"},{"kind":"word","token":"فابصرت","display":"فابصرت"},{"kind":"word","token":"السماء","display":"السماء"},{"kind":"word","token":"و","display":"و"},{"kind":"word","token":"الارض","display":"الارض"},{"kind":"word","token":"و","display":"و"},{"kind":"word","token":"كل","display":"كلّ"},{"kind":"word","token":"شيء","display":"شيء"},{"kind":"word","token":"كان","display":"كان"}]},{"source_hadith_segment":"في الدار ،  فقال عليه السّلام","translation_segment":"","segment_columns":[{"kind":"word","token":"في","display":"في"},{"kind":"word","token":"الدار","display":"الدار"},{"kind":"word","token":"فقال","display":"فقال"},{"kind":"word","token":"عليه","display":"عليه"},{"kind":"word","token":"السلام","display":"السّلام"}]},{"source_hadith_segment":":  ا تحبّ ان تكون هكذا ،  و لك ما للناس و عليك ما عليهم ؟  او تعود الي حالك و لك الجنة خالصة ؟  فقلت :","translation_segment":"","segment_columns":[{"kind":"word","token":"ا","display":"ا"},{"kind":"word","token":"تحب","display":"تحبّ"},{"kind":"word","token":"ان","display":"ان"},{"kind":"word","token":"تكون","display":"تكون"},{"kind":"word","token":"هكذا","display":"هكذا"},{"kind":"word","token":"و","display":"و"},{"kind":"word","token":"لك","display":"لك"},{"kind":"word","token":"ما","display":"ما"},{"kind":"word","token":"للناس","display":"للناس"},{"kind":"word","token":"و","display":"و"},{"kind":"word","token":"عليك","display":"عليك"},{"kind":"word","token":"ما","display":"ما"},{"kind":"word","token":"عليهم","display":"عليهم"},{"kind":"word","token":"او","display":"او"},{"kind":"word","token":"تعود","display":"تعود"},{"kind":"word","token":"الي","display":"الي"},{"kind":"word","token":"حالك","display":"حالك"},{"kind":"word","token":"و","display":"و"},{"kind":"word","token":"لك","display":"لك"},{"kind":"word","token":"الجنه","display":"الجنة"},{"kind":"word","token":"خالصه","display":"خالصة"},{"kind":"word","token":"فقلت","display":"فقلت"}]},{"source_hadith_segment":"الجنة احبّ اليّ .  فمسح يده علي عيني ،  فرجعت كما كانت","translation_segment":"","segment_columns":[{"kind":"word","token":"الجنه","display":"الجنة"},{"kind":"word","token":"احب","display":"احبّ"},{"kind":"word","token":"الي","display":"اليّ"},{"kind":"word","token":"فمسح","display":"فمسح"},{"kind":"word","token":"يده","display":"يده"},{"kind":"word","token":"علي","display":"علي"},{"kind":"word","token":"عيني","display":"عيني"},{"kind":"word","token":"فرجعت","display":"فرجعت"},{"kind":"word","token":"كما","display":"كما"},{"kind":"word","token":"كانت","display":"كانت"}]},{"source_hadith_segment":".  ثمّ قال عليه السّلام نحن جنب اللّه جلّ و عزّ ،  نحن صفوة اللّه ،  نحن خيرة اللّه ،  نحن امناء اللّه","translation_segment":"","segment_columns":[{"kind":"word","token":"ثم","display":"ثمّ"},{"kind":"word","token":"قال","display":"قال"},{"kind":"word","token":"عليه","display":"عليه"},{"kind":"word","token":"السلام","display":"السّلام"},{"kind":"word","token":"نحن","display":"نحن"},{"kind":"word","token":"جنب","display":"جنب"},{"kind":"word","token":"الله","display":"اللّه"},{"kind":"word","token":"جل","display":"جلّ"},{"kind":"word","token":"و","display":"و"},{"kind":"word","token":"عز","display":"عزّ"},{"kind":"word","token":"نحن","display":"نحن"},{"kind":"word","token":"صفوه","display":"صفوة"},{"kind":"word","token":"الله","display":"اللّه"},{"kind":"word","token":"نحن","display":"نحن"},{"kind":"word","token":"خيره","display":"خيرة"},{"kind":"word","token":"الله","display":"اللّه"},{"kind":"word","token":"نحن","display":"نحن"},{"kind":"word","token":"امناء","display":"امناء"},{"kind":"word","token":"الله","display":"اللّه"}]},{"source_hadith_segment":"،  نحن مستودع مواريث الانبياء صلّي اللّه عليهم ،  نحن حجج اللّه","translation_segment":"","segment_columns":[{"kind":"word","token":"نحن","display":"نحن"},{"kind":"word","token":"مستودع","display":"مستودع"},{"kind":"word","token":"مواريث","display":"مواريث"},{"kind":"word","token":"الانبياء","display":"الانبياء"},{"kind":"word","token":"صلي","display":"صلّي"},{"kind":"word","token":"الله","display":"اللّه"},{"kind":"word","token":"عليهم","display":"عليهم"},{"kind":"word","token":"نحن","display":"نحن"},{"kind":"word","token":"حجج","display":"حجج"},{"kind":"word","token":"الله","display":"اللّه"}]},{"source_hadith_segment":"،  نحن حبل اللّه المتين","translation_segment":"","segment_columns":[{"kind":"word","token":"نحن","display":"نحن"},{"kind":"word","token":"حبل","display":"حبل"},{"kind":"word","token":"الله","display":"اللّه"},{"kind":"word","token":"المتين","display":"المتين"}]},{"source_hadith_segment":"،  نحن صراط اللّه المستقيم ،  قال","translation_segment":"","segment_columns":[{"kind":"word","token":"نحن","display":"نحن"},{"kind":"word","token":"صراط","display":"صراط"},{"kind":"word","token":"الله","display":"اللّه"},{"kind":"word","token":"المستقيم","display":"المستقيم"},{"kind":"word","token":"قال","display":"قال"}]},{"source_hadith_segment":"اللّه تعالي :   <quranic_text> « وَ اَنَّ هٰذٰا صِرٰاطِي مُسْتَقِيماً فَاتَّبِعُوهُ وَ لاٰ تَتَّبِعُوا السُّبُلَ » </quranic_text>   <footnote> [ الانعام ۱۵۳ ] </footnote>","translation_segment":"","segment_columns":[{"kind":"word","token":"الله","display":"اللّه"},{"kind":"word","token":"تعالي","display":"تعالي"},{"kind":"tag_open","tag_name":"quranic_text"},{"kind":"word","token":"و","display":"وَ"},{"kind":"word","token":"ان","display":"اَنَّ"},{"kind":"word","token":"هذا","display":"هٰذٰا"},{"kind":"word","token":"صراطي","display":"صِرٰاطِي"},{"kind":"word","token":"مستقيما","display":"مُسْتَقِيماً"},{"kind":"word","token":"فاتبعوه","display":"فَاتَّبِعُوهُ"},{"kind":"word","token":"و","display":"وَ"},{"kind":"word","token":"لا","display":"لاٰ"},{"kind":"word","token":"تتبعوا","display":"تَتَّبِعُوا"},{"kind":"word","token":"السبل","display":"السُّبُلَ"},{"kind":"tag_close","tag_name":"quranic_text"},{"kind":"tag_open","tag_name":"footnote"},{"kind":"word","token":"الانعام","display":"الانعام"},{"kind":"word","token":"۱۵۳","display":"۱۵۳"},{"kind":"tag_close","tag_name":"footnote"}]},{"source_hadith_segment":"نحن رحمة اللّه علي المؤمنين","translation_segment":"","segment_columns":[{"kind":"word","token":"نحن","display":"نحن"},{"kind":"word","token":"رحمه","display":"رحمة"},{"kind":"word","token":"الله","display":"اللّه"},{"kind":"word","token":"علي","display":"علي"},{"kind":"word","token":"المؤمنين","display":"المؤمنين"}]},{"source_hadith_segment":"،  بنا يفتح اللّه و بنا يختم اللّه من","translation_segment":"","segment_columns":[{"kind":"word","token":"بنا","display":"بنا"},{"kind":"word","token":"يفتح","display":"يفتح"},{"kind":"word","token":"الله","display":"اللّه"},{"kind":"word","token":"و","display":"و"},{"kind":"word","token":"بنا","display":"بنا"},{"kind":"word","token":"يختم","display":"يختم"},{"kind":"word","token":"الله","display":"اللّه"},{"kind":"word","token":"من","display":"من"}]},{"source_hadith_segment":"تمسّك بنا نجا ،  و من تخلّف عنّا غوي","translation_segment":"","segment_columns":[{"kind":"word","token":"تمسك","display":"تمسّك"},{"kind":"word","token":"بنا","display":"بنا"},{"kind":"word","token":"نجا","display":"نجا"},{"kind":"word","token":"و","display":"و"},{"kind":"word","token":"من","display":"من"},{"kind":"word","token":"تخلف","display":"تخلّف"},{"kind":"word","token":"عنا","display":"عنّا"},{"kind":"word","token":"غوي","display":"غوي"}]},{"source_hadith_segment":"،  نحن القادة الغرّ المحجّلين .  ثمّ","translation_segment":"","segment_columns":[{"kind":"word","token":"نحن","display":"نحن"},{"kind":"word","token":"القاده","display":"القادة"},{"kind":"word","token":"الغر","display":"الغرّ"},{"kind":"word","token":"المحجلين","display":"المحجّلين"},{"kind":"word","token":"ثم","display":"ثمّ"}]},{"source_hadith_segment":"قال عليه السّلام :  فمن عرفنا و عرف حقّنا ،  و اخذ بامرنا ،  فهو منّا و الينا .","translation_segment":"","segment_columns":[{"kind":"word","token":"قال","display":"قال"},{"kind":"word","token":"عليه","display":"عليه"},{"kind":"word","token":"السلام","display":"السّلام"},{"kind":"word","token":"فمن","display":"فمن"},{"kind":"word","token":"عرفنا","display":"عرفنا"},{"kind":"word","token":"و","display":"و"},{"kind":"word","token":"عرف","display":"عرف"},{"kind":"word","token":"حقنا","display":"حقّنا"},{"kind":"word","token":"و","display":"و"},{"kind":"word","token":"اخذ","display":"اخذ"},{"kind":"word","token":"بامرنا","display":"بامرنا"},{"kind":"word","token":"فهو","display":"فهو"},{"kind":"word","token":"منا","display":"منّا"},{"kind":"word","token":"و","display":"و"},{"kind":"word","token":"الينا","display":"الينا"}]}]}