{"members":[{"header_text":" وَ رُوِيَ فِي صِفَةِ زِيَارَتِهِمْ رِوَايَةٌ أُخْرَى عَنْ  مُحَمَّدِ بْنِ مُسْلِمٍ قَالَ:","body_text":"قُلْتُ لِاَبِي عَبْدِ اللَّهِ عَلَيْهِ السَّلاَمُ نَزُورُ الْمَوْتَي فَقَالَ نَعَمْ قُلْتُ فَيَعْلَمُونَ بِنَا اِذَا اَتَيْنَاهُمْ قَالَ اِي وَ اللَّهِ لَيَعْلَمُونَ بِكُمْ وَ يَفْرَحُونَ بِكُمْ وَ يَسْتَاْنِسُونَ اِلَيْكُمْ قَالَ قُلْتُ فَاَيَّ شَيْءٍ نَقُولُ اِذَا اَتَيْنَاهُمْ قَالَ قُلِ اللَّهُمَّ جَافِ الْاَرْضَ عَنْ جُنُوبِهِمْ وَ صَاعِدْ اِلَيْكَ اَرْوَاحَهُمْ وَ لَقِّهِمْ مِنْكَ رِضْوَاناً وَ اَسْكِنْ اِلَيْهِمْ مِنْ رَحْمَتِكَ مَا تَصِلُ بِهِ وَحْدَتَهُمْ وَ تُؤْنِسُ بِهِ وَحْشَتَهُمْ <quranic_text>«اِنَّكَ عَليٰ كُلِّ شَيْءٍ قَدِيرٌ»</quranic_text> <footnote>[العمران۲۶]</footnote> وَ اِذَا كُنْتَ بَيْنَ الْقُبُورِ فَاقْرَاْ قُلْ هُوَ اللَّهُ اَحَدٌ اِحْدَي عَشْرَةَ مَرَّةً وَ اَهْدِ ذَلِكَ لَهُمْ فَقَدْ رُوِيَ اَنَّ اللَّهَ يُثِيبُهُ عَلَي عَدَدِ الْاَمْوَاتِ.","translation":"","aligned_body":"قُلْتُ لِاَبِي عَبْدِ اللَّهِ عَلَيْهِ السَّلاَمُ نَزُورُ الْمَوْتَي - فَقَالَ نَعَمْ قُلْتُ فَيَعْلَمُونَ بِنَا اِذَا اَتَيْنَاهُمْ قَالَ اِي وَ اللَّهِ - لَيَعْلَمُونَ بِكُمْ وَ يَفْرَحُونَ بِكُمْ وَ يَسْتَاْنِسُونَ اِلَيْكُمْ قَالَ قُلْتُ فَاَيَّ شَيْءٍ نَقُولُ اِذَا اَتَيْنَاهُمْ قَالَ قُلِ اللَّهُمَّ جَافِ الْاَرْضَ عَنْ جُنُوبِهِمْ وَ صَاعِدْ اِلَيْكَ اَرْوَاحَهُمْ وَ لَقِّهِمْ مِنْكَ رِضْوَاناً وَ اَسْكِنْ اِلَيْهِمْ مِنْ رَحْمَتِكَ مَا تَصِلُ بِهِ وَحْدَتَهُمْ وَ تُؤْنِسُ بِهِ وَحْشَتَهُمْ TAG_OPEN:quranic_text اِنَّكَ عَليٰ كُلِّ شَيْءٍ قَدِيرٌ TAG_CLOSE:quranic_text TAG_OPEN:footnote العمران۲۶ - TAG_CLOSE:footnote وَ اِذَا كُنْتَ بَيْنَ الْقُبُورِ فَاقْرَاْ قُلْ هُوَ اللَّهُ اَحَدٌ اِحْدَي عَشْرَةَ مَرَّةً وَ اَهْدِ ذَلِكَ لَهُمْ فَقَدْ رُوِيَ اَنَّ اللَّهَ يُثِيبُهُ عَلَي عَدَدِ الْاَمْوَاتِ"},{"header_text":" وَ رُوِيَ فِي صِفَةِ زِيَارَتِهِمْ رِوَايَةٌ أُخْرَى عَنْ  مُحَمَّدِ بْنِ مُسْلِمٍ قَالَ:","body_text":"قُلْتُ لِاَبِي عَبْدِ اللَّهِ عَلَيْهِ السَّلاَمُ نَزُورُ الْمَوْتَي فَقَالَ نَعَمْ قُلْتُ فَيَعْلَمُونَ بِنَا اِذَا اَتَيْنَاهُمْ قَالَ اِي وَ اللَّهِ لَيَعْلَمُونَ بِكُمْ وَ يَفْرَحُونَ بِكُمْ وَ يَسْتَاْنِسُونَ اِلَيْكُمْ قَالَ قُلْتُ فَاَيَّ شَيْءٍ نَقُولُ اِذَا اَتَيْنَاهُمْ قَالَ قُلِ اللَّهُمَّ جَافِ الْاَرْضَ عَنْ جُنُوبِهِمْ وَ صَاعِدْ اِلَيْكَ اَرْوَاحَهُمْ وَ لَقِّهِمْ مِنْكَ رِضْوَاناً وَ اَسْكِنْ اِلَيْهِمْ مِنْ رَحْمَتِكَ مَا تَصِلُ بِهِ وَحْدَتَهُمْ وَ تُؤْنِسُ وَحْشَتَهُمْ اِنَّكَ عَلَي كُلِّ شَيْءٍ قَدِيرٌ وَ اِذَا كُنْتَ بَيْنَ الْقُبُورِ فَاقْرَاْ قُلْ هُوَ اللَّهُ اَحَدٌ اِحْدَي عَشْرَةَ مَرَّةً وَ اَهْدِ ذَلِكَ لَهُمْ فَقَدْ رُوِيَ اَنَّ اللَّهَ يُثِيبُهُ عَلَي عَدَدِ الْاَمْوَاتِ.","translation":"","aligned_body":"قُلْتُ لِاَبِي عَبْدِ اللَّهِ عَلَيْهِ السَّلاَمُ نَزُورُ الْمَوْتَي - فَقَالَ نَعَمْ قُلْتُ فَيَعْلَمُونَ بِنَا اِذَا اَتَيْنَاهُمْ قَالَ اِي وَ اللَّهِ - لَيَعْلَمُونَ بِكُمْ وَ يَفْرَحُونَ بِكُمْ وَ يَسْتَاْنِسُونَ اِلَيْكُمْ قَالَ قُلْتُ فَاَيَّ شَيْءٍ نَقُولُ اِذَا اَتَيْنَاهُمْ قَالَ قُلِ اللَّهُمَّ جَافِ الْاَرْضَ عَنْ جُنُوبِهِمْ وَ صَاعِدْ اِلَيْكَ اَرْوَاحَهُمْ وَ لَقِّهِمْ مِنْكَ رِضْوَاناً وَ اَسْكِنْ اِلَيْهِمْ مِنْ رَحْمَتِكَ مَا تَصِلُ بِهِ وَحْدَتَهُمْ وَ تُؤْنِسُ - وَحْشَتَهُمْ - اِنَّكَ عَلَي كُلِّ شَيْءٍ قَدِيرٌ - - - - - وَ اِذَا كُنْتَ بَيْنَ الْقُبُورِ فَاقْرَاْ قُلْ هُوَ اللَّهُ اَحَدٌ اِحْدَي عَشْرَةَ مَرَّةً وَ اَهْدِ ذَلِكَ لَهُمْ فَقَدْ رُوِيَ اَنَّ اللَّهَ يُثِيبُهُ عَلَي عَدَدِ الْاَمْوَاتِ"},{"header_text":" 24703-2 ( الفقيه 180:1 رقم 540) محمد قال:","body_text":"قلت لابي عبد اللّٰه عليه السّلام : الموتي نزورهم فقال \"نعم \"قلت: فيعلمون بنا اذا اتيناهم فقال \"اي و اللّٰه انهم ليعلمون بكم و يفرحون بكم و يستانسون اليكم \" قال: قلت: فاي شيء نقول اذا اتيناهم قال \"قل: اللهم جاف الارض عن جنوبهم و صاعد اليك ارواحهم، و لقهم منك رضوانا، و اسكن اليهم من رحمتك ما تصل به وحدتهم، و تؤنس به وحشتهم، انك علي كل شيء قدير\".","translation":"","aligned_body":"قلت لابي عبد اللّٰه عليه السّلام - الموتي نزورهم فقال نعم قلت فيعلمون بنا اذا اتيناهم فقال اي و اللّٰه انهم ليعلمون بكم و يفرحون بكم و يستانسون اليكم قال قلت فاي شيء نقول اذا اتيناهم قال قل اللهم جاف الارض عن جنوبهم و صاعد اليك ارواحهم و لقهم منك رضوانا و اسكن اليهم من رحمتك ما تصل به وحدتهم و تؤنس به وحشتهم - انك علي كل شيء قدير - - - - - - - - - - - - - - - - - - - - - - - - - - - - - -"},{"header_text":" وَ رُوِيَ عَنْ  مُحَمَّدِ بْنِ مُسْلِمٍ أَنَّهُ قَالَ:","body_text":"قُلْتُ لِاَبِي عَبْدِ اللَّهِ عَلَيْهِ السَّلاَمُ الْمَوْتَي نَزُورُهُمْ فَقَالَ «نَعَمْ» قُلْتُ فَيَعْلَمُونَ بِنَا اِذَا اَتَيْنَاهُمْ فَقَالَ «اِي وَ اللَّهِ اِنَّهُمْ لَيَعْلَمُونَ بِكُمْ وَ يَفْرَحُونَ بِكُمْ وَ يَسْتَاْنِسُونَ اِلَيْكُمْ» قَالَ قُلْتُ فَاَيَّ شَيْءٍ نَقُولُ اِذَا اَتَيْنَاهُمْ قَالَ «قُلِ اللَّهُمَّ جَافِ الْاَرْضَ عَنْ جُنُوبِهِمْ وَ صَاعِدْ اِلَيْكَ اَرْوَاحَهُمْ وَ لَقِّهِمْ مِنْكَ رِضْوَاناً وَ اَسْكِنْ اِلَيْهِمْ مِنْ رَحْمَتِكَ مَا تَصِلُ بِهِ وَحْدَتَهُمْ وَ تُؤْنِسُ بِهِ وَحْشَتَهُمْ <quranic_text>«اِنَّكَ عَليٰ كُلِّ شَيْءٍ قَدِيرٌ»</quranic_text> <footnote>[العمران۲۶]</footnote> .","translation":"از محمد بن مسلم روایت شده که گفت: بامام صادق علیه السلام عرضکردم: آیا خوبست مردگان را زیارت کنیم‌؟ آن حضرت فرمود: آری، عرضکردم: وقتی نزد ایشان میرویم آنان متوجه ما میشوند؟ فرمود: آری بخدا قسم، ایشان متوجه آمدن شما میشوند و از عمل شما خوشحال میگردند و بشما انس میگیرند و از تنهایی بیرون می‌آیند. گوید: عرضکردم: هنگامی که نزد آنان میرویم چه بگوئیم‌؟ فرمود: این دعا را بخوان: «اللهم‌ جاف الأرض عن جنوبهم و صاعد إلیک ارواحهم و لقهم منک رضوانا، و اسکن إلیهم من رحمتک ما تصل به وحدتهم، و تونس به وحشتهم، إنک علی کل‌ شیء قدیر» یعنی: بار خدایا زمین را از پهلویهای ایشان دور ساز (کنایه از آنکه فشار قبر را از ایشان بگردان) و روانهایشان را بسوی خود بالا ببر، و از جانب خویش خشنودیت را پیشبازشان فرست، و از رحمتت همنشینی برای آنان بگمار که دلتنگی و تنهائیشان را مبدل بأنس و آرامی و وحشتشان را مبدل بأمن ساز، چرا که تو بر هر چیز توانائی.","aligned_body":"قُلْتُ لِاَبِي عَبْدِ اللَّهِ عَلَيْهِ السَّلاَمُ - الْمَوْتَي نَزُورُهُمْ فَقَالَ نَعَمْ قُلْتُ فَيَعْلَمُونَ بِنَا اِذَا اَتَيْنَاهُمْ فَقَالَ اِي وَ اللَّهِ اِنَّهُمْ لَيَعْلَمُونَ بِكُمْ وَ يَفْرَحُونَ بِكُمْ وَ يَسْتَاْنِسُونَ اِلَيْكُمْ قَالَ قُلْتُ فَاَيَّ شَيْءٍ نَقُولُ اِذَا اَتَيْنَاهُمْ قَالَ قُلِ اللَّهُمَّ جَافِ الْاَرْضَ عَنْ جُنُوبِهِمْ وَ صَاعِدْ اِلَيْكَ اَرْوَاحَهُمْ وَ لَقِّهِمْ مِنْكَ رِضْوَاناً وَ اَسْكِنْ اِلَيْهِمْ مِنْ رَحْمَتِكَ مَا تَصِلُ بِهِ وَحْدَتَهُمْ وَ تُؤْنِسُ بِهِ وَحْشَتَهُمْ TAG_OPEN:quranic_text اِنَّكَ عَليٰ كُلِّ شَيْءٍ قَدِيرٌ TAG_CLOSE:quranic_text TAG_OPEN:footnote العمران ۲۶ TAG_CLOSE:footnote - - - - - - - - - - - - - - - - - - - - - - - - -"},{"header_text":" فَمِنْ ذَلِكَ بِإِسْنَادِي إِلَى  مُحَمَّدِ بْنِ بَابَوَيْهِ فِي كِتَابِهِ  مَدِينَةِ اَلْعِلْمِ عَنْ  أَبِيهِ عَنْ  مُحَمَّدِ بْنِ يَحْيَى عَنْ  مُوسَى بْنِ اَلْحَسَنِ عَنْ  أَحْمَدَ بْنِ هِلاَلٍ اَلْعَبْرِيِّ عَنْ  عَلِيِّ بْنِ أَسْبَاطٍ عَنْ  عَبْدِ اَللَّهِ بْنِ مُحَمَّدٍ عَنْ  عَبْدِ اَللَّهِ بْنِ بُكَيْرٍ عَنْ  مُحَمَّدِ بْنِ مُسْلِمٍ قَالَ:","body_text":"قُلْتُ لِاَبِي عَبْدِ اللَّهِ عَلَيْهِ السَّلاَمُ نَزُورُ الْمَوْتَي فَقَالَ نَعَمْ قُلْتُ فَيَسْمَعُونَ بِنَا اِذَا اَتَيْنَاهُمْ قَالَ اِي وَ اللَّهِ اِنَّهُمْ لَيَعْلَمُونَ بِكُمْ وَ يَفْرَحُونَ بِكُمْ وَ يَسْتَاْنِسُونَ اِلَيْكُمْ قَالَ قُلْتُ فَاَيَّ شَيْءٍ نَقُولُ اِذَا اَتَيْنَاهُمْ قَالَ قُلِ اللَّهُمَّ جَافِ الْاَرْضَ عَنْ جُنُوبِهِمْ وَ صَاعِدْ اِلَيْكَ اَرْوَاحَهُمْ وَ لَقِّهِمْ مِنْكَ رِضْوَاناً وَ اَسْكِنْ اِلَيْهِمْ مِنْ رَحْمَتِكَ مَا تَصِلُ بِهِ وَحْدَتَهُمْ وَ تُؤْنِسُ بِهِ وَحْشَتَهُمْ <quranic_text>«اِنَّكَ عَليٰ كُلِّ شَيْءٍ قَدِيرٌ»</quranic_text> <footnote>[العمران۲۶]</footnote> .","translation":"در روایتی محمد بن مسلم می‌گوید: به امام صادق علیه السلام عرض کردم‌؟ آیا مردگان را زیارت کنیم‌؟ فرمود: بله. عرض کردم: آیا وقتی ما به زیارتشان می‌رویم، آنان صدای ما را می‌شنوند؟ فرمود: بله، به خدا سوگند، چنین است، مسلما آنان از آمدن شما خبردار شده و شادمان می‌گردند و با شما انس می‌گیرند. وی می‌گوید: عرض کردم: وقتی به زیارت ایشان رفتیم چه بگوییم‌؟ فرمود بگو: «اللهم‌، جاف الأرض عن جنوبهم، و صاعد إلیک أرواحهم، و لقهم منک رضوانا، و أسکن إلیهم من رحمتک ما تصل به وحدتهم، و تونس به وحشتهم، إنک علی کل‌ شیء قدیر.». -خداوندا، زمین را از پهلوهایشان بر کنار فرموده و جایگاهشان را وسعت ده، و ارواح آنان را به سوی خود بالا بر، و خشنودی مخصوص خود را به ایشان ارزانی دار، و از رحمت خویش چنان رحمتی به سوی آنان گسیل دار که با ارتباط‍‌ بر قرار کردن با آنان ایشان را از تنهایی نجات داده، و مونس وحشت و احساس تنهایی‌شان گردی، براستی که تو بر هر چیز توانایی.","aligned_body":"قُلْتُ لِاَبِي عَبْدِ اللَّهِ عَلَيْهِ السَّلاَمُ نَزُورُ الْمَوْتَي - فَقَالَ نَعَمْ قُلْتُ فَيَسْمَعُونَ بِنَا اِذَا اَتَيْنَاهُمْ قَالَ اِي وَ اللَّهِ اِنَّهُمْ لَيَعْلَمُونَ بِكُمْ وَ يَفْرَحُونَ بِكُمْ وَ يَسْتَاْنِسُونَ اِلَيْكُمْ قَالَ قُلْتُ فَاَيَّ شَيْءٍ نَقُولُ اِذَا اَتَيْنَاهُمْ قَالَ قُلِ اللَّهُمَّ جَافِ الْاَرْضَ عَنْ جُنُوبِهِمْ وَ صَاعِدْ اِلَيْكَ اَرْوَاحَهُمْ وَ لَقِّهِمْ مِنْكَ رِضْوَاناً وَ اَسْكِنْ اِلَيْهِمْ مِنْ رَحْمَتِكَ مَا تَصِلُ بِهِ وَحْدَتَهُمْ وَ تُؤْنِسُ بِهِ وَحْشَتَهُمْ TAG_OPEN:quranic_text اِنَّكَ عَليٰ كُلِّ شَيْءٍ قَدِيرٌ TAG_CLOSE:quranic_text TAG_OPEN:footnote العمران۲۶ - TAG_CLOSE:footnote - - - - - - - - - - - - - - - - - - - - - - - - -"},{"header_text":"وروي أيضا في صفة زيارتهم رواية أخرى عن محمد بن مسلم قال: قلت للصادق ( صلوات الله وسلامه عليه","body_text":": نزور الموتى قال: نعم. قلت: فيعلمون بنا إذا أتيناهم قال: إي والله ليعلمون بكم ويفرحون بكم ويستأنسون إليكم. قال قلت: فأي شي نقول إذا أتيناهم قال: قل: اللهم جاف الارض عن جنوبهم وصاعد إليك أرواحهم ولقهم منك رضوانا وأسكن إليهم من رحمتك ما تصل به وحدتهم وتؤنس به وحشتهم إنك على كل شي قدير","translation":"","aligned_body":"- - - - - - نزور الموتى - قال نعم قلت فيعلمون بنا إذا أتيناهم قال إي - والله - ليعلمون بكم - ويفرحون بكم - ويستأنسون إليكم قال قلت فأي شي نقول إذا أتيناهم قال قل اللهم جاف الارض عن جنوبهم - وصاعد إليك أرواحهم - ولقهم منك رضوانا - وأسكن إليهم من رحمتك ما تصل به وحدتهم - وتؤنس به وحشتهم - إنك على كل شي قدير - - - - - - - - - - - - - - - - - - - - - - - - - - - - - -"},{"header_text":" مُحَمَّدُ بْنُ عَلِيِّ بْنِ اَلْحُسَيْنِ بِإِسْنَادِهِ عَنْ  مُحَمَّدِ بْنِ مُسْلِمٍ أَنَّهُ قَالَ:","body_text":"قُلْتُ لِاَبِي عَبْدِ اللَّهِ عَلَيْهِ السَّلاَمُ الْمَوْتَي نَزُورُهُمْ قَالَ نَعَمْ اِلَي اَنْ قَالَ: قُلْتُ: فَاَيَّ شَيْءٍ نَقُولُ اِذَا اَتَيْنَاهُمْ قَالَ قُلِ اللَّهُمَّ جَافِ الْاَرْضَ عَنْ جُنُوبِهِمْ وَ صَاعِدْ اِلَيْكَ اَرْوَاحَهُمْ وَ لَقِّهِمْ مِنْكَ رِضْوَاناً وَ اَسْكِنْ اِلَيْهِمْ مِنْ رَحْمَتِكَ مَا تَصِلُ بِهِ وَحْدَتَهُمْ وَ تُؤْنِسُ بِهِ وَحْشَتَهُمْ اِنَّكَ عَلَي كُلِّ شَيْءٍ قَدِيرٌ.","translation":"","aligned_body":"قُلْتُ لِاَبِي عَبْدِ اللَّهِ عَلَيْهِ السَّلاَمُ - الْمَوْتَي نَزُورُهُمْ قَالَ نَعَمْ - - - - - - - - اِلَي اَنْ - - - - - - - - قَالَ قُلْتُ فَاَيَّ شَيْءٍ نَقُولُ اِذَا اَتَيْنَاهُمْ قَالَ قُلِ اللَّهُمَّ جَافِ الْاَرْضَ عَنْ جُنُوبِهِمْ وَ صَاعِدْ اِلَيْكَ اَرْوَاحَهُمْ وَ لَقِّهِمْ مِنْكَ رِضْوَاناً وَ اَسْكِنْ اِلَيْهِمْ مِنْ رَحْمَتِكَ مَا تَصِلُ بِهِ وَحْدَتَهُمْ وَ تُؤْنِسُ بِهِ وَحْشَتَهُمْ - اِنَّكَ عَلَي كُلِّ شَيْءٍ قَدِيرٌ - - - - - - - - - - - - - - - - - - - - - - - - - - - - - -"},{"header_text":" اَلسَّيِّدُ عَلِيُّ بْنُ طَاوُسٍ فِي  فَلاَحِ اَلسَّائِلِ ، عَنْ كِتَابِ  مَدِينَةِ اَلْعِلْمِ  لِلصَّدُوقِ عَنْ  أَبِيهِ عَنْ  مُحَمَّدِ بْنِ يَحْيَى عَنْ  مُوسَى بْنِ اَلْحَسَنِ عَنْ  أَحْمَدَ بْنِ هِلاَلٍ عَنْ  عَلِيِّ بْنِ أَسْبَاطٍ عَنْ  عَبْدِ اَللَّهِ بْنِ مُحَمَّدٍ عَنْ  عَبْدِ اَللَّهِ بْنِ بُكَيْرٍ عَنْ  مُحَمَّدِ بْنِ مُسْلِمٍ قَالَ:","body_text":"قُلْتُ لِاَبِي عَبْدِ اللَّهِ عَلَيْهِ السَّلاَمُ نَزُورُ الْمَوْتَي فَقَالَ نَعَمْ اِلَي اَنْ قَالَ قُلْتُ فَاَيَّ شَيْءٍ نَقُولُ اِذَا زُرْتُهُمْ قَالَ قُلِ اللَّهُمَّ جَافِ الْاَرْضَ عَنْ جُنُوبِهِمْ وَ صَاعِدْ اِلَيْكَ اَرْوَاحَهُمْ وَ لَقِّهِمْ مِنْكَ رِضْوَاناً وَ اَسْكِنْ اِلَيْهِمْ مِنْ رَحْمَتِكَ مَا تَصِلُ بِهِ وَحْدَتَهُمْ وَ تُؤْنِسُ بِهِ وَحْشَتَهُمْ اِنَّكَ عَلَي كُلِّ شَيْءٍ قَدِيرٌ.","translation":"","aligned_body":"قُلْتُ لِاَبِي عَبْدِ اللَّهِ عَلَيْهِ السَّلاَمُ نَزُورُ الْمَوْتَي - فَقَالَ نَعَمْ - - - - - - - - اِلَي اَنْ - - - - - - - - قَالَ قُلْتُ فَاَيَّ شَيْءٍ نَقُولُ اِذَا زُرْتُهُمْ قَالَ قُلِ اللَّهُمَّ جَافِ الْاَرْضَ عَنْ جُنُوبِهِمْ وَ صَاعِدْ اِلَيْكَ اَرْوَاحَهُمْ وَ لَقِّهِمْ مِنْكَ رِضْوَاناً وَ اَسْكِنْ اِلَيْهِمْ مِنْ رَحْمَتِكَ مَا تَصِلُ بِهِ وَحْدَتَهُمْ وَ تُؤْنِسُ بِهِ وَحْشَتَهُمْ - اِنَّكَ عَلَي كُلِّ شَيْءٍ قَدِيرٌ - - - - - - - - - - - - - - - - - - - - - - - - - - - - - -"}],"body_consensus_columns":[{"kind":"word","token":"قلت","display":"قُلْتُ"},{"kind":"word","token":"لابي","display":"لِاَبِي"},{"kind":"word","token":"عبد","display":"عَبْدِ"},{"kind":"word","token":"الله","display":"اللَّهِ"},{"kind":"word","token":"عليه","display":"عَلَيْهِ"},{"kind":"word","token":"السلام","display":"السَّلاَمُ"},{"kind":"word","token":"نزور","display":"نَزُورُ"},{"kind":"word","token":"الموتي","display":"الْمَوْتَي"},{"kind":"word","token":"نزورهم","display":"نَزُورُهُمْ"},{"kind":"word","token":"فقال","display":"فَقَالَ"},{"kind":"word","token":"نعم","display":"نَعَمْ"},{"kind":"word","token":"قلت","display":"قُلْتُ"},{"kind":"word","token":"فيعلمون","display":"فَيَعْلَمُونَ"},{"kind":"word","token":"بنا","display":"بِنَا"},{"kind":"word","token":"اذا","display":"اِذَا"},{"kind":"word","token":"اتيناهم","display":"اَتَيْنَاهُمْ"},{"kind":"word","token":"فقال","display":"فَقَالَ"},{"kind":"word","token":"اي","display":"اِي"},{"kind":"word","token":"و","display":"وَ"},{"kind":"word","token":"الله","display":"اللَّهِ"},{"kind":"word","token":"انهم","display":"اِنَّهُمْ"},{"kind":"word","token":"ليعلمون","display":"لَيَعْلَمُونَ"},{"kind":"word","token":"بكم","display":"بِكُمْ"},{"kind":"word","token":"و","display":"وَ"},{"kind":"word","token":"يفرحون","display":"يَفْرَحُونَ"},{"kind":"word","token":"بكم","display":"بِكُمْ"},{"kind":"word","token":"و","display":"وَ"},{"kind":"word","token":"يستانسون","display":"يَسْتَاْنِسُونَ"},{"kind":"word","token":"اليكم","display":"اِلَيْكُمْ"},{"kind":"word","token":"قال","display":"قَالَ"},{"kind":"word","token":"قلت","display":"قُلْتُ"},{"kind":"word","token":"فاي","display":"فَاَيَّ"},{"kind":"word","token":"شيء","display":"شَيْءٍ"},{"kind":"word","token":"نقول","display":"نَقُولُ"},{"kind":"word","token":"اذا","display":"اِذَا"},{"kind":"word","token":"اتيناهم","display":"اَتَيْنَاهُمْ"},{"kind":"word","token":"قال","display":"قَالَ"},{"kind":"word","token":"قل","display":"قُلِ"},{"kind":"word","token":"اللهم","display":"اللَّهُمَّ"},{"kind":"word","token":"جاف","display":"جَافِ"},{"kind":"word","token":"الارض","display":"الْاَرْضَ"},{"kind":"word","token":"عن","display":"عَنْ"},{"kind":"word","token":"جنوبهم","display":"جُنُوبِهِمْ"},{"kind":"word","token":"و","display":"وَ"},{"kind":"word","token":"صاعد","display":"صَاعِدْ"},{"kind":"word","token":"اليك","display":"اِلَيْكَ"},{"kind":"word","token":"ارواحهم","display":"اَرْوَاحَهُمْ"},{"kind":"word","token":"و","display":"وَ"},{"kind":"word","token":"لقهم","display":"لَقِّهِمْ"},{"kind":"word","token":"منك","display":"مِنْكَ"},{"kind":"word","token":"رضوانا","display":"رِضْوَاناً"},{"kind":"word","token":"و","display":"وَ"},{"kind":"word","token":"اسكن","display":"اَسْكِنْ"},{"kind":"word","token":"اليهم","display":"اِلَيْهِمْ"},{"kind":"word","token":"من","display":"مِنْ"},{"kind":"word","token":"رحمتك","display":"رَحْمَتِكَ"},{"kind":"word","token":"ما","display":"مَا"},{"kind":"word","token":"تصل","display":"تَصِلُ"},{"kind":"word","token":"به","display":"بِهِ"},{"kind":"word","token":"وحدتهم","display":"وَحْدَتَهُمْ"},{"kind":"word","token":"و","display":"وَ"},{"kind":"word","token":"تؤنس","display":"تُؤْنِسُ"},{"kind":"word","token":"به","display":"بِهِ"},{"kind":"word","token":"وحشتهم","display":"وَحْشَتَهُمْ"},{"kind":"tag_open","tag_name":"quranic_text"},{"kind":"word","token":"انك","display":"اِنَّكَ"},{"kind":"word","token":"علي","display":"عَليٰ"},{"kind":"word","token":"كل","display":"كُلِّ"},{"kind":"word","token":"شيء","display":"شَيْءٍ"},{"kind":"word","token":"قدير","display":"قَدِيرٌ"},{"kind":"tag_close","tag_name":"quranic_text"},{"kind":"tag_open","tag_name":"footnote"},{"kind":"word","token":"العمران","display":"العمران"},{"kind":"word","token":"۲۶","display":"۲۶"},{"kind":"tag_close","tag_name":"footnote"},{"kind":"word","token":"و","display":"وَ"},{"kind":"word","token":"اذا","display":"اِذَا"},{"kind":"word","token":"كنت","display":"كُنْتَ"},{"kind":"word","token":"بين","display":"بَيْنَ"},{"kind":"word","token":"القبور","display":"الْقُبُورِ"},{"kind":"word","token":"فاقرا","display":"فَاقْرَاْ"},{"kind":"word","token":"قل","display":"قُلْ"},{"kind":"word","token":"هو","display":"هُوَ"},{"kind":"word","token":"الله","display":"اللَّهُ"},{"kind":"word","token":"احد","display":"اَحَدٌ"},{"kind":"word","token":"احدي","display":"اِحْدَي"},{"kind":"word","token":"عشره","display":"عَشْرَةَ"},{"kind":"word","token":"مره","display":"مَرَّةً"},{"kind":"word","token":"و","display":"وَ"},{"kind":"word","token":"اهد","display":"اَهْدِ"},{"kind":"word","token":"ذلك","display":"ذَلِكَ"},{"kind":"word","token":"لهم","display":"لَهُمْ"},{"kind":"word","token":"فقد","display":"فَقَدْ"},{"kind":"word","token":"روي","display":"رُوِيَ"},{"kind":"word","token":"ان","display":"اَنَّ"},{"kind":"word","token":"الله","display":"اللَّهَ"},{"kind":"word","token":"يثيبه","display":"يُثِيبُهُ"},{"kind":"word","token":"علي","display":"عَلَي"},{"kind":"word","token":"عدد","display":"عَدَدِ"},{"kind":"word","token":"الاموات","display":"الْاَمْوَاتِ"}]}